explot/__init__.py
explot/plot.py
explot-0.0.1.dist-info/METADATA
explot-0.0.1.dist-info/WHEEL
explot-0.0.1.dist-info/RECORD
