Metadata-Version: 2.3
Name: explot
Version: 0.0.1
Summary: Various utilities to explore neural networks.
License: .github/LICENSE.md
Author: apehex
Author-email: apehex@protonmail.com
Requires-Python: >=3.10,<4.0
Classifier: License :: Other/Proprietary License
Classifier: Programming Language :: Python :: 3
Classifier: Programming Language :: Python :: 3.10
Classifier: Programming Language :: Python :: 3.11
Classifier: Programming Language :: Python :: 3.12
Classifier: Programming Language :: Python :: 3.13
Requires-Dist: matplotlib (>=3.0)
